{
        "type": "flying",
        "localizedName": "Assistant",
	    "description": "???",
        "speed": 4,
        "accel": 0.1,
        "drag": 0.01,
        "flying": true,
        "health": 300,
        "armor": 5,
        "engineOffset": 4,
		"engineSize": 1,
		"TargetAir": true,
        "circleTarget": true,
        "outlineColor": "#2d2f39",
		"trailLength": 10,
	    "weapons": [
			 {
    "type": "RepairBeamWeapon"
    "widthSinMag": 0.5,
    "beamWidth": 0.5,
    "shootY": 0,
    "repairSpeed": 3.5,
    "fractionRepairSpeed": 0.125,
    "shootCone": 15,
    "healColor": "#66f27d",
    "laserColor": "#66f27d",
    
    "targetUnits": false,
    "targetBuildings": true,
    "autoTarget": false,
    "controllable": true,
    "x": 0,
    "y": 5,
    "mirror": false,
    "rotate": false,
    
    "bullet": {
      "maxRange": 40,
    }
  }
	]
}
